datasetmaker/__init__.py
datasetmaker/api.py
datasetmaker/datapackage.py
datasetmaker/exceptions.py
datasetmaker/extensions.py
datasetmaker/merge.py
datasetmaker/models.py
datasetmaker/path.py
datasetmaker/s3.py
datasetmaker/utils.py
datasetmaker/validate.py
datasetmaker/clients/__init__.py
datasetmaker/clients/esv.py
datasetmaker/clients/hdi.py
datasetmaker/clients/meps.py
datasetmaker/clients/nobel.py
datasetmaker/clients/sipri.py
datasetmaker/clients/tax_justice.py
datasetmaker/clients/unsc.py
datasetmaker/clients/valforsk.py
datasetmaker/clients/waqi.py
datasetmaker/clients/kolada/__init__.py
datasetmaker/clients/kolada/api.py
datasetmaker/clients/kolada/client.py
datasetmaker/clients/mynewsflash/__init__.py
datasetmaker/clients/mynewsflash/client.py
datasetmaker/clients/mynewsflash/config.py
datasetmaker/clients/mynewsflash/corpus.py
datasetmaker/clients/mynewsflash/countries.py
datasetmaker/clients/mynewsflash/download.py
datasetmaker/clients/riksdagen/__init__.py
datasetmaker/clients/riksdagen/client.py
datasetmaker/clients/riksdagen/meps.py
datasetmaker/clients/scb/__init__.py
datasetmaker/clients/scb/api.py
datasetmaker/clients/scb/client.py
datasetmaker/clients/scb/election_results.py
datasetmaker/clients/scb/psu_polls.py
datasetmaker/clients/skolverket/MultiYearTable.py
datasetmaker/clients/skolverket/Table.py
datasetmaker/clients/skolverket/__init__.py
datasetmaker/clients/skolverket/api_schema.py
datasetmaker/clients/skolverket/client.py
datasetmaker/clients/skolverket/concepts.py
datasetmaker/clients/skolverket/school_registry.py
datasetmaker/clients/socialstyrelsen/__init__.py
datasetmaker/clients/socialstyrelsen/api.py
datasetmaker/clients/socialstyrelsen/client.py
datasetmaker/clients/socialstyrelsen/deaths.py
datasetmaker/clients/wikipedia/__init__.py
datasetmaker/clients/wikipedia/client.py
datasetmaker/clients/wikipedia/election_scraper.py
datasetmaker/clients/wikipedia/leader_scraper.py
datasetmaker/clients/wikipedia/utils.py
datasetmaker-0.12.33.dist-info/METADATA
datasetmaker-0.12.33.dist-info/WHEEL
datasetmaker-0.12.33.dist-info/top_level.txt
datasetmaker-0.12.33.dist-info/RECORD
