Metadata-Version: 2.1
Name: datasetmaker
Version: 0.12.33
Summary: Fetch, transform, and package data.
Home-page: UNKNOWN
Author: Datastory
Author-email: hej@datastory.org
License: UNKNOWN
Platform: UNKNOWN
Requires-Dist: boto3
Requires-Dist: botocore
Requires-Dist: bs4
Requires-Dist: ddf-utils
Requires-Dist: defusedxml
Requires-Dist: html5lib
Requires-Dist: lxml
Requires-Dist: openpyxl
Requires-Dist: pandas
Requires-Dist: requests
Requires-Dist: unidecode
